{
  "db_name": "PostgreSQL",
  "query": "\n        SELECT id, username, password, created_at\n        FROM app_user\n        WHERE username = $1\n        ",
  "describe": {
    "columns": [
      {
        "ordinal": 0,
        "name": "id",
        "type_info": "Int4"
      },
      {
        "ordinal": 1,
        "name": "username",
        "type_info": "Varchar"
      },
      {
        "ordinal": 2,
        "name": "password",
        "type_info": "Text"
      },
      {
        "ordinal": 3,
        "name": "created_at",
        "type_info": "Timestamptz"
      }
    ],
    "parameters": {
      "Left": [
        "Text"
      ]
    },
    "nullable": [
      false,
      false,
      false,
      true
    ]
  },
  "hash": "955a6886be307429a36ae892a63d4c9e09d583830578a7668590cb395756043e"
}
